{"stat.drop.emergingtechnology.greenbulb":2,"stat.flyOneCm":6594,"stat.drop.emergingtechnology.bluebulb":1,"stat.walkOneCm":9632,"stat.drop":7,"stat.jump":5,"stat.pickup.emergingtechnology.greenbulb":2,"stat.playOneMinute":3314,"stat.leaveGame":1,"stat.sneakTime":211,"stat.drop.emergingtechnology.redbulb":2,"stat.pickup.emergingtechnology.bluebulb":1,"stat.crouchOneCm":316,"stat.timeSinceDeath":3314,"stat.drop.emergingtechnology.purplebulb":2,"stat.sprintOneCm":1269,"stat.pickup.emergingtechnology.purplebulb":2,"stat.pickup.emergingtechnology.redbulb":2}